ch347api/__device.py
ch347api/__i2c.py
ch347api/__init__.py
ch347api/__spi.py
ch347api/gpio.py
ch347api/i2c.py
ch347api/spi.py
ch347api/uart.py
ch347api-0.3.2.dist-info/LICENSE
ch347api-0.3.2.dist-info/METADATA
ch347api-0.3.2.dist-info/WHEEL
ch347api-0.3.2.dist-info/top_level.txt
ch347api-0.3.2.dist-info/RECORD
