Metadata-Version: 2.1
Name: ch347api
Version: 0.3.2
Summary: A Python Library provides full access of SPI/I2C/UART settings and communication with CH347 USB-SPI/I2C/UART bridge chip in Python language.
Home-page: https://github.com/i2cy/ch347-hidapi
Author: I2cy Cloud
Author-email: i2cy@outlook.com
Project-URL: Bug Tracker, https://github.com/i2cy/ch347-hidapi/issues
Project-URL: Source Code, https://github.com/i2cy/ch347-hidapi
Project-URL: Documentation, https://github.com/i2cy/CH347-HIDAPI/blob/master/README.md
Classifier: Programming Language :: Python :: 3
Classifier: License :: OSI Approved :: MIT License
Classifier: Operating System :: OS Independent
Requires-Python: >=3.7
License-File: LICENSE
Requires-Dist: hidapi
